{"nodes": [{"id": "components_ui_button_tsx", "label": "Button.tsx", "file_type": "code", "source_file": "components/ui/Button.tsx", "source_location": "L1"}, {"id": "button_getbuttonclasses", "label": "getButtonClasses()", "file_type": "code", "source_file": "components/ui/Button.tsx", "source_location": "L46"}, {"id": "button_button", "label": "Button()", "file_type": "code", "source_file": "components/ui/Button.tsx", "source_location": "L57"}], "edges": [{"source": "components_ui_button_tsx", "target": "react", "relation": "imports_from", "confidence": "EXTRACTED", "source_file": "components/ui/Button.tsx", "source_location": "L6", "weight": 1.0}, {"source": "components_ui_button_tsx", "target": "button_module_css", "relation": "imports_from", "confidence": "EXTRACTED", "source_file": "components/ui/Button.tsx", "source_location": "L7", "weight": 1.0}, {"source": "components_ui_button_tsx", "target": "button_getbuttonclasses", "relation": "contains", "confidence": "EXTRACTED", "source_file": "components/ui/Button.tsx", "source_location": "L46", "weight": 1.0}, {"source": "components_ui_button_tsx", "target": "button_button", "relation": "contains", "confidence": "EXTRACTED", "source_file": "components/ui/Button.tsx", "source_location": "L57", "weight": 1.0}, {"source": "button_button", "target": "button_getbuttonclasses", "relation": "calls", "confidence": "EXTRACTED", "source_file": "components/ui/Button.tsx", "source_location": "L59", "weight": 1.0}]}