{"nodes": [{"id": "app_products_page_tsx", "label": "page.tsx", "file_type": "code", "source_file": "app/products/page.tsx", "source_location": "L1"}, {"id": "page_productspage", "label": "ProductsPage()", "file_type": "code", "source_file": "app/products/page.tsx", "source_location": "L18"}], "edges": [{"source": "app_products_page_tsx", "target": "next", "relation": "imports_from", "confidence": "EXTRACTED", "source_file": "app/products/page.tsx", "source_location": "L6", "weight": 1.0}, {"source": "app_products_page_tsx", "target": "layout", "relation": "imports_from", "confidence": "EXTRACTED", "source_file": "app/products/page.tsx", "source_location": "L7", "weight": 1.0}, {"source": "app_products_page_tsx", "target": "productsherosection", "relation": "imports_from", "confidence": "EXTRACTED", "source_file": "app/products/page.tsx", "source_location": "L8", "weight": 1.0}, {"source": "app_products_page_tsx", "target": "productscataloguesection", "relation": "imports_from", "confidence": "EXTRACTED", "source_file": "app/products/page.tsx", "source_location": "L9", "weight": 1.0}, {"source": "app_products_page_tsx", "target": "sections", "relation": "imports_from", "confidence": "EXTRACTED", "source_file": "app/products/page.tsx", "source_location": "L10", "weight": 1.0}, {"source": "app_products_page_tsx", "target": "page_productspage", "relation": "contains", "confidence": "EXTRACTED", "source_file": "app/products/page.tsx", "source_location": "L18", "weight": 1.0}]}